setup.py
Valle_gameoflife.egg-info/PKG-INFO
Valle_gameoflife.egg-info/SOURCES.txt
Valle_gameoflife.egg-info/dependency_links.txt
Valle_gameoflife.egg-info/not-zip-safe
Valle_gameoflife.egg-info/requires.txt
Valle_gameoflife.egg-info/top_level.txt
bin/gameoflife
bin/gameoflife.bat
gameoflife/__main__.py
gameoflife/game/Cell.py
gameoflife/game/Form.py
gameoflife/game/Runner.py
gameoflife/screens/GameOfLife.py
gameoflife/screens/Ihm.py