Metadata-Version: 1.0
Name: Valle-gameoflife
Version: 1.0.5
Summary: Conway's Game of Life for ESGI Python project.
Home-page: https://github.com/LeDixiemeHomme/Python-Game-Of-Life
Author: 2ndGroupe
Author-email: UNKNOWN
License: UNKNOWN
Platform: UNKNOWN
